llama_index/question_gen/guidance/__init__.py
llama_index/question_gen/guidance/base.py
llama_index_question_gen_guidance-0.4.1.dist-info/METADATA
llama_index_question_gen_guidance-0.4.1.dist-info/WHEEL
llama_index_question_gen_guidance-0.4.1.dist-info/licenses/LICENSE
llama_index_question_gen_guidance-0.4.1.dist-info/RECORD
